{
  "type": "FeatureCollection",
  "features": [
    {
      "type": "Feature",
      "properties": {
        "name": "SGGS NETWORK SDN. BHD.",
        "description": "Office",
        "address": "Office\n22-1, Jalan Equine 1D,\nTaman Equine, 43300\nSeri Kembangan, Selangor\nMalaysia",
        "image": "https://uploads-ssl.webflow.com/6453980466edcb7b60b5acc6/657763c26ca43b08df26e9df_SGGS-Black.svg"
  
      },
      "geometry": {
        "type": "Point",
        "coordinates": [
          101.6789256, 
          2.9963089
        ]
      }
    },
    {
      "type": "Feature",
      "properties": {
        "name": "SG.GS (HK) LIMITED",
        "description": "Office",
        "address": "Office\n10/F RM D,\nTower A, Billion Centre,\n1 Wang Kwong Road, Kowloon Bay, Kowloon, Hong Kong",
        "image": "https://uploads-ssl.webflow.com/6453980466edcb7b60b5acc6/657763c26ca43b08df26e9df_SGGS-Black.svg"
  
      },
      "geometry": {
        "type": "Point",
        "coordinates": [
          114.2061161, 
          22.32148650000001
        ]
      }
    },
    {
      "type": "Feature",
      "properties": {
        "name": "SG.GS INTERNATIONAL LTD",
        "description": "Office",
        "address": "Office\n80-83 Long Lane,\nLondon,\nEC1A 9ET\nUnited Kingdom",
        "image": "https://uploads-ssl.webflow.com/6453980466edcb7b60b5acc6/657763c26ca43b08df26e9df_SGGS-Black.svg"
  
      },
      "geometry": {
        "type": "Point",
        "coordinates": [
          -0.098546725422637, 
          51.51968165718548
        ]
      }
    },

    { "type": "Feature",
      "properties": {
        "name": "SG.GS PTE. LTD.",
        "description": "Office",
        "address": "Office\n750C Chai Chee Road\n#02-02, Viva Business Park,\nSingapore, 469003,\nSingapore",
        "image": "https://uploads-ssl.webflow.com/6453980466edcb7b60b5acc6/657763c26ca43b08df26e9df_SGGS-Black.svg"
  
      },
      "geometry": {
        "type": "Point",
        "coordinates": [
          103.920409099999901, 
          1.3233178
        ]   
      }
    }
  ]
}

